pybisp/__init__.py
pybisp/equipartition.py
pybisp/ou.py
PyBISP-1.0.1.dist-info/METADATA
PyBISP-1.0.1.dist-info/WHEEL
PyBISP-1.0.1.dist-info/top_level.txt
PyBISP-1.0.1.dist-info/RECORD
