Metadata-Version: 2.1
Name: PyBISP
Version: 1.0.1
Summary: Python library for Bayesian Inference of Stochastic Processes
Home-page: https://github.com/ronojoy/pybisp
Author: Rajesh Singh and R. Adhikari
Author-email: rsingh@imsc.res.in and  rjoy.imsc.res.in
License: MIT
Platform: Tested on Linux and Mac
